{
    "FileName": "default",
    "NumberSteps": 20,
    "UOM": "F",
    "Steps": [{
            "STy": "1",
            "P": "Fill kettle with water",
            "SP": "0",
            "STi": "0",
            "FV": "0",
            "HPos": "0",
            "BF": false,
            "PF": false,
            "S": true,
            "AF": false
        },
        {
            "STy": "1",
            "P": "Place cover on kettle and open the valve",
            "SP": "0",
            "STi": "0",
            "FV": "0",
            "HPos": "0",
            "BF": false,
            "PF": false,
            "S": true,
            "AF": false
        },
        {
            "STy": "3",
            "P": "Heating water to strike temperature of 154",
            "SP": "154",
            "STi": "0",
            "FV": "0",
            "HPos": "0",
            "BF": false,
            "PF": true,
            "S": true,
            "AF": false
        },
        {
            "STy": "1",
            "P": "Water at strike temperature. Close valve and add grains",
            "SP": "152",
            "STi": "0",
            "FV": "0",
            "HPos": "0",
            "BF": false,
            "PF": false,
            "S": true,
            "AF": true
        },
        {
            "STy": "1",
            "P": "Place cover on kettle and open valve",
            "SP": "152",
            "STi": "0",
            "FV": "0",
            "HPos": "0",
            "BF": false,
            "PF": false,
            "S": true,
            "AF": false
        },
        {
            "STy": "3",
            "P": "Heating to mash temperature of 152",
            "SP": "152",
            "STi": "0",
            "FV": "0",
            "HPos": "0",
            "BF": false,
            "PF": true,
            "S": true,
            "AF": false
        },
        {
            "STy": "4",
            "P": "Maintaining mash temperature of 152",
            "SP": "154",
            "STi": "60",
            "FV": "0",
            "HPos": "0",
            "BF": false,
            "PF": true,
            "S": true,
            "AF": false
        },
        {
            "STy": "3",
            "P": "Heating to mash out temperature of 168",
            "SP": "168",
            "STi": "0",
            "FV": "0",
            "HPos": "0",
            "BF": false,
            "PF": true,
            "S": true,
            "AF": false
        },
        {
            "STy": "4",
            "P": "Maintaining mash out temperature of 168",
            "SP": "168",
            "STi": "10",
            "FV": "0",
            "HPos": "0",
            "BF": false,
            "PF": true,
            "S": true,
            "AF": false
        },
        {
            "STy": "1",
            "P": "Mash out complete. Close valve and remove cover",
            "SP": "168",
            "STi": "0",
            "FV": "0",
            "HPos": "0",
            "BF": false,
            "PF": false,
            "S": true,
            "AF": true
        },
        {
            "STy": "1",
            "P": "Remove the grain bag",
            "SP": "190",
            "STi": "0",
            "FV": "0",
            "HPos": "0",
            "BF": false,
            "PF": false,
            "S": true,
            "AF": false
        },
        {
            "STy": "3",
            "P": "Heating wort to boiling",
            "SP": "220",
            "STi": "0",
            "FV": "0",
            "HPos": "0",
            "BF": true,
            "PF": false,
            "S": true,
            "AF": false
        },
        {
            "STy": "2",
            "P": "Boiling.  Add 60 minute hops",
            "SP": "220",
            "STi": "0",
            "FV": "0",
            "HPos": "0",
            "BF": true,
            "PF": false,
            "S": true,
            "AF": true
        },
        {
            "STy": "4",
            "P": "Maintaining boil for 50 minutes",
            "SP": "220",
            "STi": "50",
            "FV": "0",
            "HPos": "0",
            "BF": true,
            "PF": false,
            "S": true,
            "AF": false
        },
        {
            "STy": "2",
            "P": "Add 10 minute hops, whirfloc and chiller",
            "SP": "220",
            "STi": "0",
            "FV": "0",
            "HPos": "0",
            "BF": true,
            "PF": false,
            "S": true,
            "AF": true
        },
        {
            "STy": "4",
            "P": "Maintaining boil for 10 minutes",
            "SP": "220",
            "STi": "10",
            "FV": "0",
            "HPos": "0",
            "BF": true,
            "PF": false,
            "S": true,
            "AF": false
        },
        {
            "STy": "1",
            "P": "Boil complete. Open valve and turn on chiller water",
            "SP": "68",
            "STi": "0",
            "FV": "0",
            "HPos": "0",
            "BF": false,
            "PF": false,
            "S": true,
            "AF": true
        },
        {
            "STy": "5",
            "P": "Recirculate to chill",
            "SP": "68",
            "STi": "0",
            "FV": "0",
            "HPos": "0",
            "BF": false,
            "PF": false,
            "S": true,
            "AF": false
        },
        {
            "STy": "4",
            "P": "Chilling complete.  Let stand for 30 minutes",
            "SP": "0",
            "STi": "30",
            "FV": "0",
            "HPos": "0",
            "BF": false,
            "PF": false,
            "S": true,
            "AF": false
        },
        {
            "STy": "1",
            "P": "Brewing complete.  Rack to fermentor.",
            "SP": "0",
            "STi": "0",
            "FV": "0",
            "HPos": "0",
            "BF": false,
            "PF": false,
            "S": true,
            "AF": true
        }
    ]
}